MANIFEST.in
README.md
setup.cfg
setup.py
requirements/base.txt
requirements/dev.txt
xls_reader/__init__.py
xls_reader/column.py
xls_reader/data_importer.py
xls_reader/exceptions.py
xls_reader.egg-info/PKG-INFO
xls_reader.egg-info/SOURCES.txt
xls_reader.egg-info/dependency_links.txt
xls_reader.egg-info/requires.txt
xls_reader.egg-info/top_level.txt
xls_reader_test/__init__.py
xls_reader_test/bindings.py
xls_reader_test/test_column.py
xls_reader_test/test_exceptions.py
xls_reader_test/tests_negative.py
xls_reader_test/tests_positive.py