Metadata-Version: 1.0
Name: xls-reader
Version: 0.1.0
Summary: A utility to read XLS files formatted by humans
Home-page: UNKNOWN
Author: Jacek Bzdak
Author-email: jacek@askesis.pl
License: MIT
Platform: UNKNOWN
